lab1/full_adder.v
/*
module modulename(out1, out2, in1,in2,cin);
    //stuffstuffstuff instructions
endmodule
*/

module full_adder(S, Cout, A, B, Cin); 
    //order and # of arguments doesn't matter since you are going to assign them
    input A,B,Cin;
    output S, Cout;
    wire w1, w2, w3;

    xor Sresult(S,A,B,Cin);
    
    //Cout = AB + BCin + ACin
    and A_and_B (w1,A,B);
    and B_and_Cin (w2,B,Cin);
    and A_and_Cin (w3,A,Cin);
    or Cout_result (Cout,w1,w2,w3);

endmodule

lab1/full_adder_tb.v
`timescale 1 ns / 100 ps

module full_adder_tb;
    //inputs to module (reg)
    reg A;
    reg B;
    reg Cin;

    //outputs to module (wire)
    wire S;         
    wire Cout;

    //instantiate the full adder module
    full_adder adder(.S(S), .Cout(Cout), .A(A), .B(B), .Cin(Cin));
    // for the dot notation it is indicating .S in the fulladder module, 

    //testbench
    initial begin
        A =0; B=0; Cin=0;
        #80; //wait 80 time units
        $finish;
    end

    always 
        #10 A = ~A; //~ toggles the value
    always 
        #20 B = ~B;
    always 
        #40 Cin = ~Cin;

    always @(A,B,Cin) begin
        #1
        $display("A=%b, B=%b, Cin=%b => S=%b, Cout=%b", A, B, Cin, S, Cout);
    end

    initial begin
        $dumpfile("full_adder_tb.vcd"); //output file name
        $dumpvars(0, full_adder_tb); //module to capture what level, 0 means all wire
    end
    
endmodule

lab1/full_adder_tb.vcd
$date
	Thu Jan 29 15:42:17 2026
$end
$version
	Icarus Verilog
$end
$timescale
	100ps
$end
$scope module full_adder_tb $end
$var wire 1 ! S $end
$var wire 1 " Cout $end
$var reg 1 # A $end
$var reg 1 $ B $end
$var reg 1 % Cin $end
$scope module adder $end
$var wire 1 # A $end
$var wire 1 $ B $end
$var wire 1 % Cin $end
$var wire 1 " Cout $end
$var wire 1 ! S $end
$var wire 1 & w1 $end
$var wire 1 ' w2 $end
$var wire 1 ( w3 $end
$upscope $end
$upscope $end
$enddefinitions $end
$comment Show the parameter values. $end
$dumpall
$end
#0
$dumpvars
0(
0'
0&
0%
0$
0#
0"
0!
$end
#100
1!
1#
#200
0#
1$
#300
1"
0!
1&
1#
#400
0"
0&
1!
0#
0$
1%
#500
1"
0!
1(
1#
#600
0(
1'
0#
1$
#700
1!
1&
1(
1#
#800
0"
0&
0!
0'
0(
0#
0$
0%
