lab2/onebitfulladder.v
module onebitfulladder(A,B,Cin,S,Cout); //module name cannot start with number
    input A,B,Cin; //organge out is cin
    output S,Cout;
    wire w1,w2,w3,w4,w5,w6,w7;

    nand n1(w1,A,B);  //red w1
    nand n2(w2,A,w1); //black w2    
    nand n3(w3,B,w1); //w3:26
    nand n4(w4,w2,w3);                                                     
    nand n5(w5,Cin,w4); 
    nand n6(w6,w5,w4); //w4 is blue, black pointing out is w6
    nand n7(w7,Cin,w5); //w7 green pointing out
    nand n8(Cout,w5,w1);
    nand n9(S,w6,w7); //on line 50

endmodule

lab2/onebitfulladder_tb.v
`timescale 1 ns / 100 ps

module onebitfulladder_tb;
    //inputs to module (reg)
    reg A;
    reg B;
    reg Cin;

    //outputs to module (wire)
    wire S;         
    wire Cout;

    //instantiate the full adder module
    onebitfulladder adder(.S(S), .Cout(Cout), .A(A), .B(B), .Cin(Cin));
    // for the dot notation it is indicating .S in the fulladder module, 

    //testbench
    initial begin
        A =0; B=0; Cin=0;
        #80; //wait 80 time units
        $finish;
    end

    always 
        #10 A = ~A; //~ toggles the value
    always 
        #20 B = ~B;
    always 
        #40 Cin = ~Cin;

    always @(A,B,Cin) begin
        #1
        $display("A=%b, B=%b, Cin=%b => S=%b, Cout=%b", A, B, Cin, S, Cout);
    end

    initial begin
        $dumpfile("onebitfulladder.vcd"); //output file name
        $dumpvars(0, onebitfulladder_tb); //module to capture what level, 0 means all wire
    end
    
endmodule

lab2/onebitfulladder.vcd
$date
	Thu Jan 22 15:15:34 2026
$end
$version
	Icarus Verilog
$end
$timescale
	100ps
$end
$scope module onebitfulladder_tb $end
$var wire 1 ! S $end
$var wire 1 " Cout $end
$var reg 1 # A $end
$var reg 1 $ B $end
$var reg 1 % Cin $end
$scope module adder $end
$var wire 1 # A $end
$var wire 1 $ B $end
$var wire 1 % Cin $end
$var wire 1 " Cout $end
$var wire 1 ! S $end
$var wire 1 & w1 $end
$var wire 1 ' w2 $end
$var wire 1 ( w3 $end
$var wire 1 ) w4 $end
$var wire 1 * w5 $end
$var wire 1 + w6 $end
$var wire 1 , w7 $end
$upscope $end
$upscope $end
$enddefinitions $end
$comment Show the parameter values. $end
$dumpall
$end
#0
$dumpvars
1,
1+
1*
0)
1(
1'
1&
0%
0$
0#
0"
0!
$end
#100
1!
0+
1)
0'
1#
#200
1'
0(
0#
1$
#300
0!
1+
0)
1(
1"
0&
1'
1#
#400
0"
1!
1&
0,
0#
0$
1%
#500
0!
1,
1"
0*
1+
1)
0'
1#
#600
1'
0(
0#
1$
#700
1!
0,
1*
0)
1(
0&
1'
1#
#800
0"
0!
1&
1,
0#
0$
0%
