lab3/mux.v
module mux_2 #(parameter WIDTH = 32) (out,select, in0, in1);
    input select;
    input [WIDTH-1:0] in0, in1;
    output [WIDTH-1:0] out;
    assign out = select ? in1: in0;
endmodule

module mux_4 #(parameter WIDTH = 32) (out,select, in0, in1, in2, in3);
    input [1:0] select;
    input [WIDTH-1:0] in0, in1, in2, in3;
    output [WIDTH-1:0] out;
    wire [WIDTH-1:0] w1, w2;

    mux_2 #(WIDTH) first_top (w1, select[0], in0, in1);
    mux_2 #(WIDTH) first_bottom (w2, select[0], in2, in3);
    mux_2 #(WIDTH) second (out, select[1], w1, w2);
endmodule

module mux_8 #(parameter WIDTH = 32) (out,select, in0, in1, in2, in3, in4, in5, in6, in7);
    input [2:0] select;
    input [WIDTH-1:0] in0, in1, in2, in3, in4, in5, in6, in7;
    output [WIDTH-1:0] out;
    wire [WIDTH-1:0] w1, w2;

    mux_4 #(WIDTH) first_top (w1, select[1:0], in0, in1, in2, in3);
    mux_4 #(WIDTH) first_bottom (w2, select[1:0], in4, in5, in6, in7);
    mux_2 #(WIDTH) second (out, select[2], w1, w2);
endmodule

lab3/comparator.v
module comp_2 (prevEQ, prevGT, A, B, EQ, GT);
    input prevEQ, prevGT;
    input [1:0] A,B;
    output EQ,GT;
    
    /* 
    //combinatorial logic implementation
    wire A0_B0, A1_B1;
    wire gt1,gt0;

    xnor bit0_equal (A0_B0, A[0], B[0]);
    xnor bit1_equal (A1_B1, A[1], B[1]);
    and (EQ,prevEQ, A0_B0, A1_B1); //3 input AND gate (output, input1, input2, input3)
    */

    //mux implementation
    wire [2:0] select;
    assign select[2:1] = A;
    assign select[0] = B[1];

    wire mux_eq_out, mux_gt_out;

    mux_8 #(1) eq_mux(mux_eq_out,select,~B[0],1'b0,B[0],1'b0,1'b0,~B[0],1'b0,B[0]);
    mux_8 #(1) gt_mux(mux_gt_out,select,1'b0,1'b0,~B[0],1'b0,1'b1,1'b0,1'b1,~B[0]);

    and (EQ, prevEQ, ~prevGT, mux_eq_out);
    wire w1, w2;
    and (w1, prevGT, ~prevEQ);
    and (w2, prevEQ, ~prevGT, mux_gt_out);
    or (GT, w1, w2);

endmodule

module comp_4 (EQ1, GT1, A, B, EQ0, GT0);
    input EQ1, GT1;
    input [3:0] A,B;
    output EQ0, GT0;

    wire midEQ, midGT;
    comp_2 higher_bits (EQ1, GT1, A[3:2], B[3:2], midEQ, midGT);
    comp_2 lower_bits (midEQ, midGT, A[1:0], B[1:0], EQ0, GT0);

endmodule

module comp_8 (EQ1, GT1, A, B, EQ0, GT0);
    input EQ1, GT1;
    input [7:0] A,B;
    output EQ0, GT0;

    wire midEQ, midGT;
    comp_4 higher_bits (EQ1, GT1, A[7:4], B[7:4], midEQ, midGT);
    comp_4 lower_bits (midEQ, midGT, A[3:0], B[3:0], EQ0, GT0);

endmodule

lab3/comp_8_tb.v
module comp_8_tb;
    //what is reg vs wire?
    //inputs
    wire [7:0] A;
    wire [7:0] B;
    wire prevEQ, prevGT;

    //outputs
    wire EQ,GT;         

    //instantiate the 2-bit adder module
    comp_8 comparator(prevEQ, prevGT, A, B, EQ, GT);

    integer i,j; 

    assign {A, B} = i[7:0];
    assign {prevEQ, prevGT} = j[1:0];

    initial begin
        for (j = 0; j<4; j = j+1) begin
            for (i = 0; i<256; i = i+1) begin
                #20;
                $display("prevEQ=%b, prevGT=%b, A=%b, B=%b => EQ=%b, GT=%b", prevEQ, prevGT, A, B, EQ, GT);
            end
        end

        $finish; //what does this do>
    end

    initial begin
        $dumpfile("comp_8_tb.vcd"); //output file name
        $dumpvars(0, comp_8_tb); 
    end
endmodule

lab3/comp_8_tb.vcd
$date
	Thu Jan 29 16:51:46 2026
$end
$version
	Icarus Verilog
$end
$timescale
	1s
$end
$scope module comp_8_tb $end
$var wire 1 ! prevGT $end
$var wire 1 " prevEQ $end
$var wire 1 # GT $end
$var wire 1 $ EQ $end
$var wire 8 % B [7:0] $end
$var wire 8 & A [7:0] $end
$var integer 32 ' i [31:0] $end
$var integer 32 ( j [31:0] $end
$scope module comparator $end
$var wire 8 ) A [7:0] $end
$var wire 8 * B [7:0] $end
$var wire 1 " EQ1 $end
$var wire 1 ! GT1 $end
$var wire 1 + midGT $end
$var wire 1 , midEQ $end
$var wire 1 # GT0 $end
$var wire 1 $ EQ0 $end
$scope module higher_bits $end
$var wire 4 - A [3:0] $end
$var wire 4 . B [3:0] $end
$var wire 1 " EQ1 $end
$var wire 1 ! GT1 $end
$var wire 1 / midGT $end
$var wire 1 0 midEQ $end
$var wire 1 + GT0 $end
$var wire 1 , EQ0 $end
$scope module higher_bits $end
$var wire 2 1 A [1:0] $end
$var wire 2 2 B [1:0] $end
$var wire 1 0 EQ $end
$var wire 1 / GT $end
$var wire 1 " prevEQ $end
$var wire 1 ! prevGT $end
$var wire 1 3 w1 $end
$var wire 1 4 w2 $end
$var wire 3 5 select [2:0] $end
$var wire 1 6 mux_gt_out $end
$var wire 1 7 mux_eq_out $end
$scope module eq_mux $end
$var wire 1 8 in0 $end
$var wire 1 9 in1 $end
$var wire 1 : in2 $end
$var wire 1 ; in3 $end
$var wire 1 < in4 $end
$var wire 1 = in5 $end
$var wire 1 > in6 $end
$var wire 1 ? in7 $end
$var wire 3 @ select [2:0] $end
$var wire 1 A w2 $end
$var wire 1 B w1 $end
$var wire 1 7 out $end
$var parameter 32 C WIDTH $end
$scope module first_bottom $end
$var wire 1 < in0 $end
$var wire 1 = in1 $end
$var wire 1 > in2 $end
$var wire 1 ? in3 $end
$var wire 2 D select [1:0] $end
$var wire 1 E w2 $end
$var wire 1 F w1 $end
$var wire 1 A out $end
$var parameter 32 G WIDTH $end
$scope module first_bottom $end
$var wire 1 > in0 $end
$var wire 1 ? in1 $end
$var wire 1 H select $end
$var wire 1 E out $end
$var parameter 32 I WIDTH $end
$upscope $end
$scope module first_top $end
$var wire 1 < in0 $end
$var wire 1 = in1 $end
$var wire 1 J select $end
$var wire 1 F out $end
$var parameter 32 K WIDTH $end
$upscope $end
$scope module second $end
$var wire 1 F in0 $end
$var wire 1 E in1 $end
$var wire 1 L select $end
$var wire 1 A out $end
$var parameter 32 M WIDTH $end
$upscope $end
$upscope $end
$scope module first_top $end
$var wire 1 8 in0 $end
$var wire 1 9 in1 $end
$var wire 1 : in2 $end
$var wire 1 ; in3 $end
$var wire 2 N select [1:0] $end
$var wire 1 O w2 $end
$var wire 1 P w1 $end
$var wire 1 B out $end
$var parameter 32 Q WIDTH $end
$scope module first_bottom $end
$var wire 1 : in0 $end
$var wire 1 ; in1 $end
$var wire 1 R select $end
$var wire 1 O out $end
$var parameter 32 S WIDTH $end
$upscope $end
$scope module first_top $end
$var wire 1 8 in0 $end
$var wire 1 9 in1 $end
$var wire 1 T select $end
$var wire 1 P out $end
$var parameter 32 U WIDTH $end
$upscope $end
$scope module second $end
$var wire 1 P in0 $end
$var wire 1 O in1 $end
$var wire 1 V select $end
$var wire 1 B out $end
$var parameter 32 W WIDTH $end
$upscope $end
$upscope $end
$scope module second $end
$var wire 1 B in0 $end
$var wire 1 A in1 $end
$var wire 1 X select $end
$var wire 1 7 out $end
$var parameter 32 Y WIDTH $end
$upscope $end
$upscope $end
$scope module gt_mux $end
$var wire 1 Z in0 $end
$var wire 1 [ in1 $end
$var wire 1 \ in2 $end
$var wire 1 ] in3 $end
$var wire 1 ^ in4 $end
$var wire 1 _ in5 $end
$var wire 1 ` in6 $end
$var wire 1 a in7 $end
$var wire 3 b select [2:0] $end
$var wire 1 c w2 $end
$var wire 1 d w1 $end
$var wire 1 6 out $end
$var parameter 32 e WIDTH $end
$scope module first_bottom $end
$var wire 1 ^ in0 $end
$var wire 1 _ in1 $end
$var wire 1 ` in2 $end
$var wire 1 a in3 $end
$var wire 2 f select [1:0] $end
$var wire 1 g w2 $end
$var wire 1 h w1 $end
$var wire 1 c out $end
$var parameter 32 i WIDTH $end
$scope module first_bottom $end
$var wire 1 ` in0 $end
$var wire 1 a in1 $end
$var wire 1 j select $end
$var wire 1 g out $end
$var parameter 32 k WIDTH $end
$upscope $end
$scope module first_top $end
$var wire 1 ^ in0 $end
$var wire 1 _ in1 $end
$var wire 1 l select $end
$var wire 1 h out $end
$var parameter 32 m WIDTH $end
$upscope $end
$scope module second $end
$var wire 1 h in0 $end
$var wire 1 g in1 $end
$var wire 1 n select $end
$var wire 1 c out $end
$var parameter 32 o WIDTH $end
$upscope $end
$upscope $end
$scope module first_top $end
$var wire 1 Z in0 $end
$var wire 1 [ in1 $end
$var wire 1 \ in2 $end
$var wire 1 ] in3 $end
$var wire 2 p select [1:0] $end
$var wire 1 q w2 $end
$var wire 1 r w1 $end
$var wire 1 d out $end
$var parameter 32 s WIDTH $end
$scope module first_bottom $end
$var wire 1 \ in0 $end
$var wire 1 ] in1 $end
$var wire 1 t select $end
$var wire 1 q out $end
$var parameter 32 u WIDTH $end
$upscope $end
$scope module first_top $end
$var wire 1 Z in0 $end
$var wire 1 [ in1 $end
$var wire 1 v select $end
$var wire 1 r out $end
$var parameter 32 w WIDTH $end
$upscope $end
$scope module second $end
$var wire 1 r in0 $end
$var wire 1 q in1 $end
$var wire 1 x select $end
$var wire 1 d out $end
$var parameter 32 y WIDTH $end
$upscope $end
$upscope $end
$scope module second $end
$var wire 1 d in0 $end
$var wire 1 c in1 $end
$var wire 1 z select $end
$var wire 1 6 out $end
$var parameter 32 { WIDTH $end
$upscope $end
$upscope $end
$upscope $end
$scope module lower_bits $end
$var wire 2 | A [1:0] $end
$var wire 2 } B [1:0] $end
$var wire 1 , EQ $end
$var wire 1 + GT $end
$var wire 1 0 prevEQ $end
$var wire 1 / prevGT $end
$var wire 1 ~ w1 $end
$var wire 1 !" w2 $end
$var wire 3 "" select [2:0] $end
$var wire 1 #" mux_gt_out $end
$var wire 1 $" mux_eq_out $end
$scope module eq_mux $end
$var wire 1 %" in0 $end
$var wire 1 &" in1 $end
$var wire 1 '" in2 $end
$var wire 1 (" in3 $end
$var wire 1 )" in4 $end
$var wire 1 *" in5 $end
$var wire 1 +" in6 $end
$var wire 1 ," in7 $end
$var wire 3 -" select [2:0] $end
$var wire 1 ." w2 $end
$var wire 1 /" w1 $end
$var wire 1 $" out $end
$var parameter 32 0" WIDTH $end
$scope module first_bottom $end
$var wire 1 )" in0 $end
$var wire 1 *" in1 $end
$var wire 1 +" in2 $end
$var wire 1 ," in3 $end
$var wire 2 1" select [1:0] $end
$var wire 1 2" w2 $end
$var wire 1 3" w1 $end
$var wire 1 ." out $end
$var parameter 32 4" WIDTH $end
$scope module first_bottom $end
$var wire 1 +" in0 $end
$var wire 1 ," in1 $end
$var wire 1 5" select $end
$var wire 1 2" out $end
$var parameter 32 6" WIDTH $end
$upscope $end
$scope module first_top $end
$var wire 1 )" in0 $end
$var wire 1 *" in1 $end
$var wire 1 7" select $end
$var wire 1 3" out $end
$var parameter 32 8" WIDTH $end
$upscope $end
$scope module second $end
$var wire 1 3" in0 $end
$var wire 1 2" in1 $end
$var wire 1 9" select $end
$var wire 1 ." out $end
$var parameter 32 :" WIDTH $end
$upscope $end
$upscope $end
$scope module first_top $end
$var wire 1 %" in0 $end
$var wire 1 &" in1 $end
$var wire 1 '" in2 $end
$var wire 1 (" in3 $end
$var wire 2 ;" select [1:0] $end
$var wire 1 <" w2 $end
$var wire 1 =" w1 $end
$var wire 1 /" out $end
$var parameter 32 >" WIDTH $end
$scope module first_bottom $end
$var wire 1 '" in0 $end
$var wire 1 (" in1 $end
$var wire 1 ?" select $end
$var wire 1 <" out $end
$var parameter 32 @" WIDTH $end
$upscope $end
$scope module first_top $end
$var wire 1 %" in0 $end
$var wire 1 &" in1 $end
$var wire 1 A" select $end
$var wire 1 =" out $end
$var parameter 32 B" WIDTH $end
$upscope $end
$scope module second $end
$var wire 1 =" in0 $end
$var wire 1 <" in1 $end
$var wire 1 C" select $end
$var wire 1 /" out $end
$var parameter 32 D" WIDTH $end
$upscope $end
$upscope $end
$scope module second $end
$var wire 1 /" in0 $end
$var wire 1 ." in1 $end
$var wire 1 E" select $end
$var wire 1 $" out $end
$var parameter 32 F" WIDTH $end
$upscope $end
$upscope $end
$scope module gt_mux $end
$var wire 1 G" in0 $end
$var wire 1 H" in1 $end
$var wire 1 I" in2 $end
$var wire 1 J" in3 $end
$var wire 1 K" in4 $end
$var wire 1 L" in5 $end
$var wire 1 M" in6 $end
$var wire 1 N" in7 $end
$var wire 3 O" select [2:0] $end
$var wire 1 P" w2 $end
$var wire 1 Q" w1 $end
$var wire 1 #" out $end
$var parameter 32 R" WIDTH $end
$scope module first_bottom $end
$var wire 1 K" in0 $end
$var wire 1 L" in1 $end
$var wire 1 M" in2 $end
$var wire 1 N" in3 $end
$var wire 2 S" select [1:0] $end
$var wire 1 T" w2 $end
$var wire 1 U" w1 $end
$var wire 1 P" out $end
$var parameter 32 V" WIDTH $end
$scope module first_bottom $end
$var wire 1 M" in0 $end
$var wire 1 N" in1 $end
$var wire 1 W" select $end
$var wire 1 T" out $end
$var parameter 32 X" WIDTH $end
$upscope $end
$scope module first_top $end
$var wire 1 K" in0 $end
$var wire 1 L" in1 $end
$var wire 1 Y" select $end
$var wire 1 U" out $end
$var parameter 32 Z" WIDTH $end
$upscope $end
$scope module second $end
$var wire 1 U" in0 $end
$var wire 1 T" in1 $end
$var wire 1 [" select $end
$var wire 1 P" out $end
$var parameter 32 \" WIDTH $end
$upscope $end
$upscope $end
$scope module first_top $end
$var wire 1 G" in0 $end
$var wire 1 H" in1 $end
$var wire 1 I" in2 $end
$var wire 1 J" in3 $end
$var wire 2 ]" select [1:0] $end
$var wire 1 ^" w2 $end
$var wire 1 _" w1 $end
$var wire 1 Q" out $end
$var parameter 32 `" WIDTH $end
$scope module first_bottom $end
$var wire 1 I" in0 $end
$var wire 1 J" in1 $end
$var wire 1 a" select $end
$var wire 1 ^" out $end
$var parameter 32 b" WIDTH $end
$upscope $end
$scope module first_top $end
$var wire 1 G" in0 $end
$var wire 1 H" in1 $end
$var wire 1 c" select $end
$var wire 1 _" out $end
$var parameter 32 d" WIDTH $end
$upscope $end
$scope module second $end
$var wire 1 _" in0 $end
$var wire 1 ^" in1 $end
$var wire 1 e" select $end
$var wire 1 Q" out $end
$var parameter 32 f" WIDTH $end
$upscope $end
$upscope $end
$scope module second $end
$var wire 1 Q" in0 $end
$var wire 1 P" in1 $end
$var wire 1 g" select $end
$var wire 1 #" out $end
$var parameter 32 h" WIDTH $end
$upscope $end
$upscope $end
$upscope $end
$upscope $end
$scope module lower_bits $end
$var wire 4 i" A [3:0] $end
$var wire 4 j" B [3:0] $end
$var wire 1 , EQ1 $end
$var wire 1 + GT1 $end
$var wire 1 k" midGT $end
$var wire 1 l" midEQ $end
$var wire 1 # GT0 $end
$var wire 1 $ EQ0 $end
$scope module higher_bits $end
$var wire 2 m" A [1:0] $end
$var wire 2 n" B [1:0] $end
$var wire 1 l" EQ $end
$var wire 1 k" GT $end
$var wire 1 , prevEQ $end
$var wire 1 + prevGT $end
$var wire 1 o" w1 $end
$var wire 1 p" w2 $end
$var wire 3 q" select [2:0] $end
$var wire 1 r" mux_gt_out $end
$var wire 1 s" mux_eq_out $end
$scope module eq_mux $end
$var wire 1 t" in0 $end
$var wire 1 u" in1 $end
$var wire 1 v" in2 $end
$var wire 1 w" in3 $end
$var wire 1 x" in4 $end
$var wire 1 y" in5 $end
$var wire 1 z" in6 $end
$var wire 1 {" in7 $end
$var wire 3 |" select [2:0] $end
$var wire 1 }" w2 $end
$var wire 1 ~" w1 $end
$var wire 1 s" out $end
$var parameter 32 !# WIDTH $end
$scope module first_bottom $end
$var wire 1 x" in0 $end
$var wire 1 y" in1 $end
$var wire 1 z" in2 $end
$var wire 1 {" in3 $end
$var wire 2 "# select [1:0] $end
$var wire 1 ## w2 $end
$var wire 1 $# w1 $end
$var wire 1 }" out $end
$var parameter 32 %# WIDTH $end
$scope module first_bottom $end
$var wire 1 z" in0 $end
$var wire 1 {" in1 $end
$var wire 1 &# select $end
$var wire 1 ## out $end
$var parameter 32 '# WIDTH $end
$upscope $end
$scope module first_top $end
$var wire 1 x" in0 $end
$var wire 1 y" in1 $end
$var wire 1 (# select $end
$var wire 1 $# out $end
$var parameter 32 )# WIDTH $end
$upscope $end
$scope module second $end
$var wire 1 $# in0 $end
$var wire 1 ## in1 $end
$var wire 1 *# select $end
$var wire 1 }" out $end
$var parameter 32 +# WIDTH $end
$upscope $end
$upscope $end
$scope module first_top $end
$var wire 1 t" in0 $end
$var wire 1 u" in1 $end
$var wire 1 v" in2 $end
$var wire 1 w" in3 $end
$var wire 2 ,# select [1:0] $end
$var wire 1 -# w2 $end
$var wire 1 .# w1 $end
$var wire 1 ~" out $end
$var parameter 32 /# WIDTH $end
$scope module first_bottom $end
$var wire 1 v" in0 $end
$var wire 1 w" in1 $end
$var wire 1 0# select $end
$var wire 1 -# out $end
$var parameter 32 1# WIDTH $end
$upscope $end
$scope module first_top $end
$var wire 1 t" in0 $end
$var wire 1 u" in1 $end
$var wire 1 2# select $end
$var wire 1 .# out $end
$var parameter 32 3# WIDTH $end
$upscope $end
$scope module second $end
$var wire 1 .# in0 $end
$var wire 1 -# in1 $end
$var wire 1 4# select $end
$var wire 1 ~" out $end
$var parameter 32 5# WIDTH $end
$upscope $end
$upscope $end
$scope module second $end
$var wire 1 ~" in0 $end
$var wire 1 }" in1 $end
$var wire 1 6# select $end
$var wire 1 s" out $end
$var parameter 32 7# WIDTH $end
$upscope $end
$upscope $end
$scope module gt_mux $end
$var wire 1 8# in0 $end
$var wire 1 9# in1 $end
$var wire 1 :# in2 $end
$var wire 1 ;# in3 $end
$var wire 1 <# in4 $end
$var wire 1 =# in5 $end
$var wire 1 ># in6 $end
$var wire 1 ?# in7 $end
$var wire 3 @# select [2:0] $end
$var wire 1 A# w2 $end
$var wire 1 B# w1 $end
$var wire 1 r" out $end
$var parameter 32 C# WIDTH $end
$scope module first_bottom $end
$var wire 1 <# in0 $end
$var wire 1 =# in1 $end
$var wire 1 ># in2 $end
$var wire 1 ?# in3 $end
$var wire 2 D# select [1:0] $end
$var wire 1 E# w2 $end
$var wire 1 F# w1 $end
$var wire 1 A# out $end
$var parameter 32 G# WIDTH $end
$scope module first_bottom $end
$var wire 1 ># in0 $end
$var wire 1 ?# in1 $end
$var wire 1 H# select $end
$var wire 1 E# out $end
$var parameter 32 I# WIDTH $end
$upscope $end
$scope module first_top $end
$var wire 1 <# in0 $end
$var wire 1 =# in1 $end
$var wire 1 J# select $end
$var wire 1 F# out $end
$var parameter 32 K# WIDTH $end
$upscope $end
$scope module second $end
$var wire 1 F# in0 $end
$var wire 1 E# in1 $end
$var wire 1 L# select $end
$var wire 1 A# out $end
$var parameter 32 M# WIDTH $end
$upscope $end
$upscope $end
$scope module first_top $end
$var wire 1 8# in0 $end
$var wire 1 9# in1 $end
$var wire 1 :# in2 $end
$var wire 1 ;# in3 $end
$var wire 2 N# select [1:0] $end
$var wire 1 O# w2 $end
$var wire 1 P# w1 $end
$var wire 1 B# out $end
$var parameter 32 Q# WIDTH $end
$scope module first_bottom $end
$var wire 1 :# in0 $end
$var wire 1 ;# in1 $end
$var wire 1 R# select $end
$var wire 1 O# out $end
$var parameter 32 S# WIDTH $end
$upscope $end
$scope module first_top $end
$var wire 1 8# in0 $end
$var wire 1 9# in1 $end
$var wire 1 T# select $end
$var wire 1 P# out $end
$var parameter 32 U# WIDTH $end
$upscope $end
$scope module second $end
$var wire 1 P# in0 $end
$var wire 1 O# in1 $end
$var wire 1 V# select $end
$var wire 1 B# out $end
$var parameter 32 W# WIDTH $end
$upscope $end
$upscope $end
$scope module second $end
$var wire 1 B# in0 $end
$var wire 1 A# in1 $end
$var wire 1 X# select $end
$var wire 1 r" out $end
$var parameter 32 Y# WIDTH $end
$upscope $end
$upscope $end
$upscope $end
$scope module lower_bits $end
$var wire 2 Z# A [1:0] $end
$var wire 2 [# B [1:0] $end
$var wire 1 $ EQ $end
$var wire 1 # GT $end
$var wire 1 l" prevEQ $end
$var wire 1 k" prevGT $end
$var wire 1 \# w1 $end
$var wire 1 ]# w2 $end
$var wire 3 ^# select [2:0] $end
$var wire 1 _# mux_gt_out $end
$var wire 1 `# mux_eq_out $end
$scope module eq_mux $end
$var wire 1 a# in0 $end
$var wire 1 b# in1 $end
$var wire 1 c# in2 $end
$var wire 1 d# in3 $end
$var wire 1 e# in4 $end
$var wire 1 f# in5 $end
$var wire 1 g# in6 $end
$var wire 1 h# in7 $end
$var wire 3 i# select [2:0] $end
$var wire 1 j# w2 $end
$var wire 1 k# w1 $end
$var wire 1 `# out $end
$var parameter 32 l# WIDTH $end
$scope module first_bottom $end
$var wire 1 e# in0 $end
$var wire 1 f# in1 $end
$var wire 1 g# in2 $end
$var wire 1 h# in3 $end
$var wire 2 m# select [1:0] $end
$var wire 1 n# w2 $end
$var wire 1 o# w1 $end
$var wire 1 j# out $end
$var parameter 32 p# WIDTH $end
$scope module first_bottom $end
$var wire 1 g# in0 $end
$var wire 1 h# in1 $end
$var wire 1 q# select $end
$var wire 1 n# out $end
$var parameter 32 r# WIDTH $end
$upscope $end
$scope module first_top $end
$var wire 1 e# in0 $end
$var wire 1 f# in1 $end
$var wire 1 s# select $end
$var wire 1 o# out $end
$var parameter 32 t# WIDTH $end
$upscope $end
$scope module second $end
$var wire 1 o# in0 $end
$var wire 1 n# in1 $end
$var wire 1 u# select $end
$var wire 1 j# out $end
$var parameter 32 v# WIDTH $end
$upscope $end
$upscope $end
$scope module first_top $end
$var wire 1 a# in0 $end
$var wire 1 b# in1 $end
$var wire 1 c# in2 $end
$var wire 1 d# in3 $end
$var wire 2 w# select [1:0] $end
$var wire 1 x# w2 $end
$var wire 1 y# w1 $end
$var wire 1 k# out $end
$var parameter 32 z# WIDTH $end
$scope module first_bottom $end
$var wire 1 c# in0 $end
$var wire 1 d# in1 $end
$var wire 1 {# select $end
$var wire 1 x# out $end
$var parameter 32 |# WIDTH $end
$upscope $end
$scope module first_top $end
$var wire 1 a# in0 $end
$var wire 1 b# in1 $end
$var wire 1 }# select $end
$var wire 1 y# out $end
$var parameter 32 ~# WIDTH $end
$upscope $end
$scope module second $end
$var wire 1 y# in0 $end
$var wire 1 x# in1 $end
$var wire 1 !$ select $end
$var wire 1 k# out $end
$var parameter 32 "$ WIDTH $end
$upscope $end
$upscope $end
$scope module second $end
$var wire 1 k# in0 $end
$var wire 1 j# in1 $end
$var wire 1 #$ select $end
$var wire 1 `# out $end
$var parameter 32 $$ WIDTH $end
$upscope $end
$upscope $end
$scope module gt_mux $end
$var wire 1 %$ in0 $end
$var wire 1 &$ in1 $end
$var wire 1 '$ in2 $end
$var wire 1 ($ in3 $end
$var wire 1 )$ in4 $end
$var wire 1 *$ in5 $end
$var wire 1 +$ in6 $end
$var wire 1 ,$ in7 $end
$var wire 3 -$ select [2:0] $end
$var wire 1 .$ w2 $end
$var wire 1 /$ w1 $end
$var wire 1 _# out $end
$var parameter 32 0$ WIDTH $end
$scope module first_bottom $end
$var wire 1 )$ in0 $end
$var wire 1 *$ in1 $end
$var wire 1 +$ in2 $end
$var wire 1 ,$ in3 $end
$var wire 2 1$ select [1:0] $end
$var wire 1 2$ w2 $end
$var wire 1 3$ w1 $end
$var wire 1 .$ out $end
$var parameter 32 4$ WIDTH $end
$scope module first_bottom $end
$var wire 1 +$ in0 $end
$var wire 1 ,$ in1 $end
$var wire 1 5$ select $end
$var wire 1 2$ out $end
$var parameter 32 6$ WIDTH $end
$upscope $end
$scope module first_top $end
$var wire 1 )$ in0 $end
$var wire 1 *$ in1 $end
$var wire 1 7$ select $end
$var wire 1 3$ out $end
$var parameter 32 8$ WIDTH $end
$upscope $end
$scope module second $end
$var wire 1 3$ in0 $end
$var wire 1 2$ in1 $end
$var wire 1 9$ select $end
$var wire 1 .$ out $end
$var parameter 32 :$ WIDTH $end
$upscope $end
$upscope $end
$scope module first_top $end
$var wire 1 %$ in0 $end
$var wire 1 &$ in1 $end
$var wire 1 '$ in2 $end
$var wire 1 ($ in3 $end
$var wire 2 ;$ select [1:0] $end
$var wire 1 <$ w2 $end
$var wire 1 =$ w1 $end
$var wire 1 /$ out $end
$var parameter 32 >$ WIDTH $end
$scope module first_bottom $end
$var wire 1 '$ in0 $end
$var wire 1 ($ in1 $end
$var wire 1 ?$ select $end
$var wire 1 <$ out $end
$var parameter 32 @$ WIDTH $end
$upscope $end
$scope module first_top $end
$var wire 1 %$ in0 $end
$var wire 1 &$ in1 $end
$var wire 1 A$ select $end
$var wire 1 =$ out $end
$var parameter 32 B$ WIDTH $end
$upscope $end
$scope module second $end
$var wire 1 =$ in0 $end
$var wire 1 <$ in1 $end
$var wire 1 C$ select $end
$var wire 1 /$ out $end
$var parameter 32 D$ WIDTH $end
$upscope $end
$upscope $end
$scope module second $end
$var wire 1 /$ in0 $end
$var wire 1 .$ in1 $end
$var wire 1 E$ select $end
$var wire 1 _# out $end
$var parameter 32 F$ WIDTH $end
$upscope $end
$upscope $end
$upscope $end
$upscope $end
$upscope $end
$upscope $end
$enddefinitions $end
$comment Show the parameter values. $end
$dumpall
b1 F$
b1 D$
b1 B$
b1 @$
b1 >$
b1 :$
b1 8$
b1 6$
b1 4$
b1 0$
b1 $$
b1 "$
b1 ~#
b1 |#
b1 z#
b1 v#
b1 t#
b1 r#
b1 p#
b1 l#
b1 Y#
b1 W#
b1 U#
b1 S#
b1 Q#
b1 M#
b1 K#
b1 I#
b1 G#
b1 C#
b1 7#
b1 5#
b1 3#
b1 1#
b1 /#
b1 +#
b1 )#
b1 '#
b1 %#
b1 !#
b1 h"
b1 f"
b1 d"
b1 b"
b1 `"
b1 \"
b1 Z"
b1 X"
b1 V"
b1 R"
b1 F"
b1 D"
b1 B"
b1 @"
b1 >"
b1 :"
b1 8"
b1 6"
b1 4"
b1 0"
b1 {
b1 y
b1 w
b1 u
b1 s
b1 o
b1 m
b1 k
b1 i
b1 e
b1 Y
b1 W
b1 U
b1 S
b1 Q
b1 M
b1 K
b1 I
b1 G
b1 C
$end
#0
$dumpvars
0E$
0C$
0A$
0?$
0=$
1<$
b0 ;$
09$
07$
05$
13$
12$
b0 1$
0/$
1.$
b0 -$
1,$
1+$
0*$
1)$
0($
1'$
0&$
0%$
0#$
0!$
0}#
0{#
1y#
0x#
b0 w#
0u#
0s#
0q#
0o#
0n#
b0 m#
1k#
0j#
b0 i#
0h#
0g#
1f#
0e#
0d#
0c#
0b#
1a#
1`#
0_#
b0 ^#
0]#
0\#
b0 [#
b0 Z#
0X#
0V#
0T#
0R#
0P#
1O#
b0 N#
0L#
0J#
0H#
1F#
1E#
b0 D#
0B#
1A#
b0 @#
1?#
1>#
0=#
1<#
0;#
1:#
09#
08#
06#
04#
02#
00#
1.#
0-#
b0 ,#
0*#
0(#
0&#
0$#
0##
b0 "#
1~"
0}"
b0 |"
0{"
0z"
1y"
0x"
0w"
0v"
0u"
1t"
1s"
0r"
b0 q"
0p"
0o"
b0 n"
b0 m"
0l"
0k"
b0 j"
b0 i"
0g"
0e"
0c"
0a"
0_"
1^"
b0 ]"
0["
0Y"
0W"
1U"
1T"
b0 S"
0Q"
1P"
b0 O"
1N"
1M"
0L"
1K"
0J"
1I"
0H"
0G"
0E"
0C"
0A"
0?"
1="
0<"
b0 ;"
09"
07"
05"
03"
02"
b0 1"
1/"
0."
b0 -"
0,"
0+"
1*"
0)"
0("
0'"
0&"
1%"
1$"
0#"
b0 ""
0!"
0~
b0 }
b0 |
0z
0x
0v
0t
0r
1q
b0 p
0n
0l
0j
1h
1g
b0 f
0d
1c
b0 b
1a
1`
0_
1^
0]
1\
0[
0Z
0X
0V
0T
0R
1P
0O
b0 N
0L
0J
0H
0F
0E
b0 D
1B
0A
b0 @
0?
0>
1=
0<
0;
0:
09
18
17
06
b0 5
04
03
b0 2
b0 1
00
0/
b0 .
b0 -
0,
0+
b0 *
b0 )
b0 (
b0 '
b0 &
b0 %
0$
0#
0"
0!
$end
#20
0`#
0k#
0y#
0<$
0a#
1x#
0f#
0'$
0,$
1c#
1h#
b1 [#
b1 j"
b1 %
b1 *
b1 '
#40
1j#
0.$
0`#
1o#
03$
0k#
1}#
1{#
1s#
1q#
1A$
1?$
17$
15$
0y#
0<$
b1 w#
b1 m#
b1 ;$
b1 1$
1a#
0x#
1f#
1'$
1,$
b1 ^#
b1 i#
b1 -$
0c#
0h#
b10 [#
b10 j"
b10 %
b10 *
b10 '
#60
0j#
0o#
02$
0a#
0f#
1n#
0'$
0,$
1c#
1h#
b11 [#
b11 j"
b11 %
b11 *
b11 '
#80
1`#
0s"
1k#
1.$
0~"
1y#
1<$
13$
0j#
0.#
0O#
0}#
0{#
0s#
0q#
0A$
0?$
07$
05$
0o#
12$
0t"
1-#
0y"
0:#
0?#
b0 w#
b0 m#
b0 ;$
b0 1$
1a#
1f#
0n#
1'$
1,$
1v"
1{"
b0 ^#
b0 i#
b0 -$
0c#
0h#
b1 n"
b0 [#
b100 j"
b100 %
b100 *
b100 '
#100
0`#
0k#
0y#
0<$
0a#
1x#
0f#
0'$
0,$
1c#
1h#
b1 [#
b101 j"
b101 %
b101 *
b101 '
#120
1j#
0.$
0`#
1o#
03$
0k#
1}#
1{#
1s#
1q#
1A$
1?$
17$
15$
0y#
0<$
b1 w#
b1 m#
b1 ;$
b1 1$
1a#
0x#
1f#
1'$
1,$
b1 ^#
b1 i#
b1 -$
0c#
0h#
b10 [#
b110 j"
b110 %
b110 *
b110 '
#140
0j#
0o#
02$
0a#
0f#
1n#
0'$
0,$
1c#
1h#
b11 [#
b111 j"
b111 %
b111 *
b111 '
